hypergolix/__init__.py
hypergolix/__main__.py
hypergolix/accounting.py
hypergolix/app.py
hypergolix/bootstrapping.py
hypergolix/cli.py
hypergolix/comms.py
hypergolix/config.py
hypergolix/core.py
hypergolix/daemon.py
hypergolix/dispatch.py
hypergolix/embed.py
hypergolix/exceptions.py
hypergolix/gao.py
hypergolix/hypothetical.py
hypergolix/inquisition.py
hypergolix/ipc.py
hypergolix/lawyer.py
hypergolix/librarian.py
hypergolix/logutils.py
hypergolix/objproxy.py
hypergolix/persistence.py
hypergolix/postal.py
hypergolix/privateer.py
hypergolix/remotes.py
hypergolix/rolodex.py
hypergolix/service.py
hypergolix/undertaker.py
hypergolix/utils.py
hypergolix/winpath.py
hypergolix-0.1.0.dist-info/DESCRIPTION.rst
hypergolix-0.1.0.dist-info/METADATA
hypergolix-0.1.0.dist-info/RECORD
hypergolix-0.1.0.dist-info/WHEEL
hypergolix-0.1.0.dist-info/entry_points.txt
hypergolix-0.1.0.dist-info/metadata.json
hypergolix-0.1.0.dist-info/top_level.txt
