Metadata-Version: 2.0
Name: hypergolix
Version: 0.1.0
Summary: A python Golix client.
Home-page: https://github.com/Muterra/py_hypergolix
Author: Muterra, Inc
Author-email: badg@muterra.io
License: LGPL
Keywords: hypergolix,IoT,internet of things,golix,encryption,security,privacy,private,identity,sharing
Platform: UNKNOWN
Classifier: Development Status :: 3 - Alpha
Classifier: Intended Audience :: Developers
Classifier: Topic :: Software Development
Classifier: Topic :: Utilities
Classifier: License :: OSI Approved :: GNU Lesser General Public License v2 or later (LGPLv2+)
Classifier: Programming Language :: Python :: 3.5
Requires-Dist: certifi
Requires-Dist: cryptography (>=1.6)
Requires-Dist: daemoniker (>=0.2.3)
Requires-Dist: golix[full] (>=0.1.6)
Requires-Dist: loopa (>=0.0.2)
Requires-Dist: pycryptodome (>=3.4.3)
Requires-Dist: websockets (>=3.2)
Provides-Extra: dev
Provides-Extra: test
